docs/conf.py
docs/index.rst
docs/make.bat
docs/requirements.txt
ut_eco/__init__.py
ut_eco/__version__.py
ut_eco/cfg.py
ut_eco/cfg.rst.yml
ut_eco/cfgde.py
ut_eco/cfgen.py
ut_eco/doc.py
ut_eco/py.typed
ut_eco/taskin.py
ut_eco/taskout.py
ut_eco/utils.py
ut_eco/verify.py
ut_eco/rst/__init__.py
ut_eco/rst/taskioc.py
ut_eco/rst/utils.py
ut_eco/xls/__init__.py
ut_eco/xls/py.typed
ut_eco/xls/taskioc.py
ut_eco/xls/utils.py
ut_eco-2.0.0.20251020.dist-info/licenses/LICENSE.txt
ut_eco-2.0.0.20251020.dist-info/METADATA
ut_eco-2.0.0.20251020.dist-info/WHEEL
ut_eco-2.0.0.20251020.dist-info/top_level.txt
ut_eco-2.0.0.20251020.dist-info/RECORD
