Metadata-Version: 2.4
Name: ut_eco
Version: 2.0.0.20251020
Summary: Utilities for EcoVadis IQ Processing.
Author-email: Bernd Stroehle <bernd.stroehle@gmail.com>
Maintainer-email: Bernd Stroehle <bernd.stroehle@gmail.com>
License-Expression: MIT AND (Apache-2.0 OR BSD-2-Clause)
Project-URL: Source Code, https://github.com/bs2910/ut_eco/tree/master
Project-URL: Homepage, https://kosakya.de/
Project-URL: Documentation, https://ut-eco.readthedocs.io/en/latest
Project-URL: Apache-2.0 License, https://apache.org/licenses/LICENSE-2.0
Project-URL: GPLv3 License, https://www.gnu.org/licenses/gpl-3.0.en.html
Classifier: Development Status :: 5 - Production/Stable
Classifier: Intended Audience :: Developers
Classifier: Operating System :: OS Independent
Classifier: Programming Language :: Python :: 3.10
Classifier: Natural Language :: English
Classifier: Topic :: Software Development :: Libraries :: Python Modules
Requires-Python: >=3.11
License-File: LICENSE.txt
Requires-Dist: geopy>=2.4.1
Requires-Dist: numpy>=2.3.3
Requires-Dist: openpyxl>=3.1.5
Requires-Dist: pandas>=2.3.3
Requires-Dist: postal_codes_tools>=1.1.3
Requires-Dist: pycountry>=24.6.1
Requires-Dist: ut_aod>=1.4.5.20251009
Requires-Dist: ut_dfr>=1.1.1.20250915
Requires-Dist: ut_dic>=1.5.5.20251011
Requires-Dist: ut_doa>=1.1.0.20251005
Requires-Dist: ut_log>=1.3.4.20251009
Requires-Dist: ut_tod>=1.4.1.20250927
Requires-Dist: ut_xls>=1.6.2.20251012
Dynamic: license-file
